{
	"section":"411",
	"versions":[
	{
		"version":"0",
		"short_title":"The Chairman",
		"text":"(a) The Chairman shall be the presiding officer of the Council.\n(b) When the Office of Mayor is vacant, the Chairman shall act in his stead. While the Chairman is Acting Mayor he shall not exercise any of his authority as Chairman or member of the Council.",
		"source": {"stat":"87 Stat. 788","cite":"411", "date":"1973-12-24"}
	}
	],
	"code":"1-204.11",
	"history": "Dec. 24, 1973, 87 Stat. 788, Pub. L. 93-198, title IV, ยง 411.",
	"title":"4",
	"part":"A",
	"subpart":"2"
}